augmenty/__init__.py
augmenty/about.py
augmenty/augment_utilities.py
augmenty/keyboard.py
augmenty/meta.json
augmenty/util.py
augmenty/character/__init__.py
augmenty/character/casing.py
augmenty/character/replace.py
augmenty/character/spacing.py
augmenty/character/swap.py
augmenty/doc/__init__.py
augmenty/doc/casing.py
augmenty/doc/subset.py
augmenty/lang/__init__.py
augmenty/lang/da/__init__.py
augmenty/lang/da/augmenters.py
augmenty/lang/da/keyboard.py
augmenty/lang/de/__init__.py
augmenty/lang/de/keyboard.py
augmenty/lang/el/__init__.py
augmenty/lang/el/keyboard.py
augmenty/lang/en/__init__.py
augmenty/lang/en/keyboard.py
augmenty/lang/es/__init__.py
augmenty/lang/es/keyboard.py
augmenty/lang/fr/__init__.py
augmenty/lang/fr/keyboard.py
augmenty/lang/hu/__init__.py
augmenty/lang/hu/keyboard.py
augmenty/lang/it/__init__.py
augmenty/lang/it/keyboard.py
augmenty/lang/lt/__init__.py
augmenty/lang/lt/keyboard.py
augmenty/lang/mk/__init__.py
augmenty/lang/mk/keyboard.py
augmenty/lang/nb/__init__.py
augmenty/lang/nb/keyboard.py
augmenty/lang/nl/__init__.py
augmenty/lang/nl/keyboard.py
augmenty/lang/pl/__init__.py
augmenty/lang/pl/keyboard.py
augmenty/lang/pt/__init__.py
augmenty/lang/pt/keyboard.py
augmenty/lang/ro/__init__.py
augmenty/lang/ro/keyboard.py
augmenty/lang/ru/__init__.py
augmenty/lang/ru/keyboard.py
augmenty/span/__init__.py
augmenty/span/entities.py
augmenty/span/utils.py
augmenty/token/__init__.py
augmenty/token/casing.py
augmenty/token/insert.py
augmenty/token/replace.py
augmenty/token/spacing.py
augmenty/token/static_embedding_util.py
augmenty/token/swap.py
augmenty/token/wordnet_util.py
augmenty-1.4.4.dist-info/LICENSE
augmenty-1.4.4.dist-info/METADATA
augmenty-1.4.4.dist-info/WHEEL
augmenty-1.4.4.dist-info/top_level.txt
augmenty-1.4.4.dist-info/RECORD
