Metadata-Version: 2.1
Name: augmenty
Version: 1.4.4
Summary: An augmentation library based on SpaCy for joint augmentation of text and labels.
Author-email: Kenneth Enevoldsen <kennethcenevoldsen@gmail.com>
License: MIT License
Project-URL: Homepage, https://github.com/KennethEnevoldsen/augmenty
Project-URL: Documentation, https://kennethenevoldsen.github.io/augmenty/
Project-URL: Repository, https://github.com/KennethEnevoldsen/augmenty
Keywords: nlp,NLP,spaCy,text analysis,natural language processing,text mining,augmentation,data augmentation,data science,machine learning,deep learning
Classifier: Development Status :: 5 - Production/Stable
Classifier: Environment :: Console
Classifier: Intended Audience :: Developers
Classifier: Intended Audience :: Science/Research
Classifier: Topic :: Scientific/Engineering
Classifier: Topic :: Scientific/Engineering :: Artificial Intelligence
Classifier: License :: OSI Approved :: MIT License
Classifier: Operating System :: POSIX :: Linux
Classifier: Operating System :: MacOS :: MacOS X
Classifier: Operating System :: Microsoft :: Windows
Classifier: Programming Language :: Python :: 3
Classifier: Programming Language :: Python :: 3.8
Classifier: Programming Language :: Python :: 3.9
Classifier: Programming Language :: Python :: 3.10
Classifier: Programming Language :: Python :: 3.11
Requires-Python: >=3.8
License-File: LICENSE
Requires-Dist: spacy >=3.2.0
Requires-Dist: catalogue >=2.0.4
Requires-Dist: thinc >=8.0.8
Requires-Dist: pydantic >=1.8.2
Requires-Dist: numpy >=1.15.0
Provides-Extra: all
Requires-Dist: nltk >=3.6.7 ; extra == 'all'
Provides-Extra: da
Requires-Dist: dacy >=2.3.1 ; extra == 'da'
Provides-Extra: dev
Requires-Dist: cruft >=2.0.0 ; extra == 'dev'
Requires-Dist: pyright >=1.1.343 ; extra == 'dev'
Requires-Dist: ruff >=0.0.254 ; extra == 'dev'
Requires-Dist: pyproject-parser[cli,readme] >=0.9.1 ; extra == 'dev'
Provides-Extra: docs
Requires-Dist: sphinx ==5.3.0 ; extra == 'docs'
Requires-Dist: furo ==2022.12.7 ; extra == 'docs'
Requires-Dist: sphinx-copybutton >=0.5.1 ; extra == 'docs'
Requires-Dist: sphinxext-opengraph >=0.7.3 ; extra == 'docs'
Requires-Dist: sphinx-design >=0.3.0 ; extra == 'docs'
Requires-Dist: myst-nb >=0.6.0 ; extra == 'docs'
Provides-Extra: tests
Requires-Dist: pytest <8.0.0,>=7.1.3 ; extra == 'tests'
Requires-Dist: pytest-cov >=3.0.0 ; extra == 'tests'
Requires-Dist: pytest-lazy-fixture >=0.6.3 ; extra == 'tests'
Requires-Dist: pytest-timeout >=2.1.0 ; extra == 'tests'
Provides-Extra: tutorials
Requires-Dist: jupyter >=1.0.0 ; extra == 'tutorials'
Requires-Dist: faker ==13.13.0 ; extra == 'tutorials'
